PagePathRAG/__init__.py
PagePathRAG/page_path_rag.py
PagePathRAG/PathRAG/PathRAG.py
PagePathRAG/PathRAG/__init__.py
PagePathRAG/PathRAG/base.py
PagePathRAG/PathRAG/llm.py
PagePathRAG/PathRAG/operate.py
PagePathRAG/PathRAG/prompt.py
PagePathRAG/PathRAG/storage.py
PagePathRAG/PathRAG/utils.py
pagepathrag-0.1.2.dist-info/licenses/LICENSE
pagepathrag-0.1.2.dist-info/METADATA
pagepathrag-0.1.2.dist-info/WHEEL
pagepathrag-0.1.2.dist-info/top_level.txt
pagepathrag-0.1.2.dist-info/RECORD
