Metadata-Version: 2.4
Name: PagePathRAG
Version: 0.1.2
Summary: 基于PathRAG的页面路径检索增强生成系统 - 专门用于将UI交互路径转化为知识图谱并进行智能查询的Python库
Home-page: https://github.com/your-username/PagePathRAG
Author: PagePathRAG Team
Author-email: PagePathRAG Team <cnatom@icloud.com>
Maintainer-email: PagePathRAG Team <cnatom@icloud.com>
License: MIT License
Project-URL: Homepage, https://github.com/your-username/PagePathRAG
Project-URL: Documentation, https://github.com/your-username/PagePathRAG#readme
Project-URL: Repository, https://github.com/your-username/PagePathRAG.git
Project-URL: Bug Tracker, https://github.com/your-username/PagePathRAG/issues
Keywords: rag,ui,path,knowledge-graph,llm,embedding,retrieval,ai
Classifier: Development Status :: 3 - Alpha
Classifier: Intended Audience :: Developers
Classifier: Topic :: Software Development :: Libraries :: Python Modules
Classifier: Topic :: Scientific/Engineering :: Artificial Intelligence
Classifier: Topic :: Text Processing :: Linguistic
Classifier: License :: OSI Approved :: MIT License
Classifier: Programming Language :: Python :: 3
Classifier: Programming Language :: Python :: 3.8
Classifier: Programming Language :: Python :: 3.9
Classifier: Programming Language :: Python :: 3.10
Classifier: Programming Language :: Python :: 3.11
Classifier: Operating System :: OS Independent
Requires-Python: >=3.8
License-File: LICENSE
Requires-Dist: accelerate
Requires-Dist: aioboto3
Requires-Dist: aiohttp
Requires-Dist: graspologic
Requires-Dist: hnswlib
Requires-Dist: nano-vectordb
Requires-Dist: neo4j
Requires-Dist: networkx
Requires-Dist: ollama
Requires-Dist: openai
Requires-Dist: oracledb
Requires-Dist: psycopg[binary,pool]
Requires-Dist: pymilvus
Requires-Dist: pymongo
Requires-Dist: pymysql
Requires-Dist: pyvis
Requires-Dist: sqlalchemy
Requires-Dist: tenacity
Requires-Dist: tiktoken
Requires-Dist: torch
Requires-Dist: transformers
Requires-Dist: xxhash
Provides-Extra: dev
Requires-Dist: pytest>=6.0; extra == "dev"
Requires-Dist: pytest-asyncio; extra == "dev"
Requires-Dist: black; extra == "dev"
Requires-Dist: isort; extra == "dev"
Requires-Dist: flake8; extra == "dev"
Requires-Dist: mypy; extra == "dev"
Requires-Dist: pre-commit; extra == "dev"
Provides-Extra: test
Requires-Dist: pytest>=6.0; extra == "test"
Requires-Dist: pytest-asyncio; extra == "test"
Requires-Dist: pytest-cov; extra == "test"
Dynamic: author
Dynamic: home-page
Dynamic: license-file
Dynamic: requires-python
